pwnup/__init__.py
pwnup/pwnup.py
pwnup/run.py
pwnup/version.py
pwnup-1.0.7.dist-info/DESCRIPTION.rst
pwnup-1.0.7.dist-info/METADATA
pwnup-1.0.7.dist-info/RECORD
pwnup-1.0.7.dist-info/WHEEL
pwnup-1.0.7.dist-info/entry_points.txt
pwnup-1.0.7.dist-info/metadata.json
pwnup-1.0.7.dist-info/top_level.txt
