Metadata-Version: 2.0
Name: pwnup
Version: 1.0.7
Summary: A utility to scaffold out pwntools projects
Home-page: https://github.com/vitapluvia/pwnup
Author: vitapluvia
Author-email: vitapluvia [at] gmail.com
License: MIT
Keywords: pwn security automation cli clients
Platform: UNKNOWN
Classifier: Topic :: Security
Classifier: Environment :: Console
Classifier: Operating System :: OS Independent
Classifier: License :: OSI Approved :: MIT License
Classifier: Programming Language :: Python :: 2.7
Classifier: Intended Audience :: Developers
Classifier: Development Status :: 3 - Alpha
Requires-Dist: pwntools
Requires-Dist: pyserial
